{"chunk_definitions":[{"chunk_id":"csetup_chunk","chunk_label":"Setup","document_id":"E4C8C3B6","expansion_state":0,"options":{"engine":"r","include":false,"label":"Setup"},"row":17,"row_count":1,"visible":true},{"chunk_id":"c9558b8rlke4w","chunk_label":"Load and Clean Data","document_id":"E4C8C3B6","expansion_state":0,"options":{"engine":"r","label":"Load and Clean Data"},"row":38,"row_count":1,"visible":true},{"chunk_id":"cfijhseosrtvh","chunk_label":"Explore Missing Data in Original Dataset","document_id":"1188D043","expansion_state":0,"options":{"engine":"r","label":"Explore Missing Data in Original Dataset"},"row":51,"row_count":1,"visible":true},{"chunk_id":"c1n8g29ayl52h","chunk_label":"Ampute Function","document_id":"1188D043","expansion_state":0,"options":{"engine":"r","label":"Ampute Function"},"row":99,"row_count":1,"visible":true},{"chunk_id":"ctm2bqc1uos68","chunk_label":"unnamed-chunk-1","document_id":"1188D043","expansion_state":0,"options":{"engine":"r","label":"unnamed-chunk-234"},"row":118,"row_count":1,"visible":true},{"chunk_id":"cedy6bg8zkckf","chunk_label":"Listwise Deletion Method","document_id":"1188D043","expansion_state":0,"options":{"engine":"r","label":"Listwise Deletion Method"},"row":129,"row_count":1,"visible":true},{"chunk_id":"cpx57f00zo099","chunk_label":"Mean/Mode Imputation","document_id":"1188D043","expansion_state":0,"options":{"engine":"r","label":"Mean/Mode Imputation"},"row":184,"row_count":1,"visible":true},{"chunk_id":"co71s55nljh8y","chunk_label":"Random Imputation","document_id":"1188D043","expansion_state":0,"options":{"engine":"r","label":"Random Imputation"},"row":215,"row_count":1,"visible":true},{"chunk_id":"clhkx7zc40397","chunk_label":"unnamed-chunk-2","document_id":"1188D043","expansion_state":0,"options":{"engine":"r","label":"unnamed-chunk-14"},"row":245,"row_count":1,"visible":true},{"chunk_id":"caeen09gn5lho","chunk_label":"Hotdecking","document_id":"1188D043","expansion_state":0,"options":{"engine":"r","label":"Hotdecking "},"row":270,"row_count":1,"visible":true},{"chunk_id":"clvy9qhyrigyo","chunk_label":"Regression Imputation","document_id":"1188D043","expansion_state":0,"options":{"engine":"r","label":"Regression Imputation"},"row":317,"row_count":1,"visible":true},{"chunk_id":"c5gdmun5y3eh0","chunk_label":"Regression Imputation with Noise","document_id":"1188D043","expansion_state":0,"options":{"engine":"r","label":"Regression Imputation with Noise"},"row":372,"row_count":1,"visible":true},{"chunk_id":"c461hdixw0201","chunk_label":"unnamed-chunk-3","document_id":"1188D043","expansion_state":0,"options":{"engine":"r","label":"unnamed-chunk-1"},"row":382,"row_count":1,"visible":true},{"chunk_id":"c3sr689mxebwk","chunk_label":"MI Summary","document_id":"1188D043","expansion_state":0,"options":{"engine":"r","label":"MI Summary"},"row":387,"row_count":1,"visible":true},{"chunk_id":"cwrnlsqiro8kj","chunk_label":"MI Histogram","document_id":"1188D043","expansion_state":0,"options":{"engine":"r","label":"MI Histogram"},"row":393,"row_count":1,"visible":true},{"chunk_id":"cyuxilrxe5332","chunk_label":"MI Image","document_id":"1188D043","expansion_state":0,"options":{"engine":"r","label":"MI Image"},"row":400,"row_count":1,"visible":true},{"chunk_id":"cp28sj2xp7ba0","chunk_label":"unnamed-chunk-4","document_id":"1188D043","expansion_state":0,"options":{"engine":"r","label":"unnamed-chunk-2"},"row":405,"row_count":1,"visible":true},{"chunk_id":"c5ks5siq9opah","chunk_label":"MI Command","document_id":"1188D043","expansion_state":0,"options":{"engine":"r","label":"MI Command"},"row":412,"row_count":1,"visible":true},{"chunk_id":"c7sczvb5mhl1h","chunk_label":"Trace Plots from MI model","document_id":"1188D043","expansion_state":0,"options":{"engine":"r","label":"Trace Plots from MI model"},"row":442,"row_count":1,"visible":true},{"chunk_id":"ce6gi2hi5pnc9","chunk_label":"unnamed-chunk-5","document_id":"1188D043","expansion_state":0,"options":{"engine":"r","label":"unnamed-chunk-6"},"row":447,"row_count":1,"visible":true},{"chunk_id":"cucjvmhcixmdd","chunk_label":"unnamed-chunk-6","document_id":"1188D043","expansion_state":0,"options":{"engine":"r","label":"unnamed-chunk-3"},"row":456,"row_count":1,"visible":true},{"chunk_id":"ct89gazy4w3gl","chunk_label":"unnamed-chunk-7","document_id":"1188D043","expansion_state":0,"options":{"engine":"r","label":"unnamed-chunk-4"},"row":460,"row_count":1,"visible":true},{"chunk_id":"c1nwscegtus90","chunk_label":"unnamed-chunk-9","document_id":"1188D043","expansion_state":0,"options":{"engine":"r","label":"unnamed-chunk-9"},"row":469,"row_count":1,"visible":true},{"chunk_id":"cizx4ps0rvwcw","chunk_label":"unnamed-chunk-10","document_id":"1188D043","expansion_state":0,"options":{"engine":"r","label":"unnamed-chunk-243"},"row":536,"row_count":1,"visible":true}],"chunk_rendered_width":600,"doc_write_time":1552947059}